pyspare/__init__.py
pyspare/deco/__init__.py
pyspare/deco/deco_crostab/__init__.py
pyspare/deco/deco_entries/__init__.py
pyspare/deco/deco_entries/deco_dict.py
pyspare/deco/deco_entries/deco_entries.py
pyspare/deco/deco_entries/deco_object.py
pyspare/deco/deco_json/__init__.py
pyspare/deco/deco_matrix/__init__.py
pyspare/deco/deco_node/__init__.py
pyspare/deco/deco_node/helpers/__init__.py
pyspare/deco/deco_node/helpers/mutate_key_pad.py
pyspare/deco/deco_node/preset/__init__.py
pyspare/deco/deco_node/render/__init__.py
pyspare/deco/deco_node/render/render_entries.py
pyspare/deco/deco_node/render/render_string.py
pyspare/deco/deco_node/render/render_vector.py
pyspare/deco/deco_samples/__init__.py
pyspare/deco/deco_str/__init__.py
pyspare/deco/deco_table/__init__.py
pyspare/deco/deco_vector/__init__.py
pyspare/deco/deco_vector/deco_vector.py
pyspare/logger/__init__.py
pyspare/logger/logger.py
pyspare/logger/says/__init__.py
pyspare/logger/says/pal.py
pyspare/logger/says/says.py
pyspare/logger/says/singleton.py
pyspare/margin/__init__.py
pyspare/margin/crostab_margin/__init__.py
pyspare/margin/entries_margin/__init__.py
pyspare/margin/entries_margin/entries_margin.py
pyspare/margin/matrix_margin/__init__.py
pyspare/margin/matrix_margin/matrix_margin.py
pyspare/margin/matrix_margin/sizing.py
pyspare/margin/table_margin/__init__.py
pyspare/margin/utils/__init__.py
pyspare/margin/vector_margin/__init__.py
pyspare/margin/vector_margin/marginize.py
pyspare/margin/vector_margin/sizing.py
pyspare/margin/vector_margin/vector_margin.py
pyspare/padder/__init__.py
pyspare/padder/crostab_padder/__init__.py
pyspare/padder/entries_padder/__init__.py
pyspare/padder/matrix_padder/__init__.py
pyspare/padder/series_padder/__init__.py
pyspare/padder/table_padder/__init__.py
pyspare/padder/vector_padder/__init__.py
pyspare-0.0.12.dist-info/WHEEL
pyspare-0.0.12.dist-info/METADATA
pyspare-0.0.12.dist-info/RECORD
